README.md
setup.cfg
setup.py
download_url/__init__.py
download_url/download_url.py
download_url.egg-info/PKG-INFO
download_url.egg-info/SOURCES.txt
download_url.egg-info/dependency_links.txt
download_url.egg-info/top_level.txt