Metadata-Version: 1.1
Name: download-url
Version: 3.0.0
Summary: Função que faz o download de arquivos através de URLs informadas
Home-page: https://github.com/FAntoniasse/download_url
Author: Fabrício Antoniasse
Author-email: fabricio.antoniasse@hotmail.com
License: MIT
Project-URL: Código fonte, https://github.com/FAntoniasse/download_url
Project-URL: Download, https://github.com/FAntoniasse/download_url/download_url2.rar
Keywords: download_url
Platform: UNKNOWN
Classifier: Development Status :: 5 - Production/Stable
Classifier: Intended Audience :: Developers
Classifier: License :: OSI Approved :: MIT License
Classifier: Natural Language :: Portuguese (Brazilian)
Classifier: Operating System :: OS Independent
